[
{
"file": "IMG_7747_30880_32549.mp4",
"corte": "IMG_7747_30880_32549.mov",
"fuente": "IMG_7747",
"frames": 101
},
{
"file": "IMG_7747_32970_36050.mp4",
"corte": "IMG_7747_32970_36050.mov",
"fuente": "IMG_7747",
"frames": 185
},
{
"file": "IMG_7747_36650_36980.mp4",
"corte": "IMG_7747_36650_36980.mov",
"fuente": "IMG_7747",
"frames": 20
},
{
"file": "IMG_7747_4740_9040.mp4",
"corte": "IMG_7747_4740_9040.mov",
"fuente": "IMG_7747",
"frames": 258
},
{
"file": "IMG_7747_57260_58930.mp4",
"corte": "IMG_7747_57260_58930.mov",
"fuente": "IMG_7747",
"frames": 101
},
{
"file": "IMG_7747_60050_64140.mp4",
"corte": "IMG_7747_60050_64140.mov",
"fuente": "IMG_7747",
"frames": 246
},
{
"file": "IMG_7747_67980_70720.mp4",
"corte": "IMG_7747_67980_70720.mov",
"fuente": "IMG_7747",
"frames": 165
},
{
"file": "IMG_7749_12530_13930.mp4",
"corte": "IMG_7749_12530_13930.mov",
"fuente": "IMG_7749",
"frames": 84
},
{
"file": "IMG_7749_14570_23620.mp4",
"corte": "IMG_7749_14570_23620.mov",
"fuente": "IMG_7749",
"frames": 543
},
{
"file": "IMG_7749_40900_42460.mp4",
"corte": "IMG_7749_40900_42460.mov",
"fuente": "IMG_7749",
"frames": 94
},
{
"file": "IMG_7749_45640_46790.mp4",
"corte": "IMG_7749_45640_46790.mov",
"fuente": "IMG_7749",
"frames": 69
},
{
"file": "IMG_7749_47110_49850.mp4",
"corte": "IMG_7749_47110_49850.mov",
"fuente": "IMG_7749",
"frames": 165
},
{
"file": "IMG_7749_52000_54510.mp4",
"corte": "IMG_7749_52000_54510.mov",
"fuente": "IMG_7749",
"frames": 151
},
{
"file": "IMG_7749_59540_61230.mp4",
"corte": "IMG_7749_59540_61230.mov",
"fuente": "IMG_7749",
"frames": 102
},
{
"file": "IMG_7749_61750_65099.mp4",
"corte": "IMG_7749_61750_65099.mov",
"fuente": "IMG_7749",
"frames": 201
},
{
"file": "IMG_7749_76140_79540.mp4",
"corte": "IMG_7749_76140_79540.mov",
"fuente": "IMG_7749",
"frames": 204
},
{
"file": "IMG_7750_120420_121650.mp4",
"corte": "IMG_7750_120420_121650.mov",
"fuente": "IMG_7750",
"frames": 74
},
{
"file": "IMG_7750_122810_123560.mp4",
"corte": "IMG_7750_122810_123560.mov",
"fuente": "IMG_7750",
"frames": 45
},
{
"file": "IMG_7750_125160_129739.mp4",
"corte": "IMG_7750_125160_129739.mov",
"fuente": "IMG_7750",
"frames": 275
},
{
"file": "IMG_7750_153800_158000.mp4",
"corte": "IMG_7750_153800_158000.mov",
"fuente": "IMG_7750",
"frames": 252
},
{
"file": "IMG_7750_160880_162720.mp4",
"corte": "IMG_7750_160880_162720.mov",
"fuente": "IMG_7750",
"frames": 111
},
{
"file": "IMG_7750_165540_168040.mp4",
"corte": "IMG_7750_165540_168040.mov",
"fuente": "IMG_7750",
"frames": 150
},
{
"file": "IMG_7750_170700_172960.mp4",
"corte": "IMG_7750_170700_172960.mov",
"fuente": "IMG_7750",
"frames": 136
},
{
"file": "IMG_7750_30320_31180.mp4",
"corte": "IMG_7750_30320_31180.mov",
"fuente": "IMG_7750",
"frames": 52
},
{
"file": "IMG_7750_35840_36470.mp4",
"corte": "IMG_7750_35840_36470.mov",
"fuente": "IMG_7750",
"frames": 38
},
{
"file": "IMG_7750_37650_43200.mp4",
"corte": "IMG_7750_37650_43200.mov",
"fuente": "IMG_7750",
"frames": 333
},
{
"file": "IMG_7750_51800_54890.mp4",
"corte": "IMG_7750_51800_54890.mov",
"fuente": "IMG_7750",
"frames": 186
},
{
"file": "IMG_7750_55270_58230.mp4",
"corte": "IMG_7750_55270_58230.mov",
"fuente": "IMG_7750",
"frames": 178
},
{
"file": "IMG_7750_59470_60080.mp4",
"corte": "IMG_7750_59470_60080.mov",
"fuente": "IMG_7750",
"frames": 37
},
{
"file": "IMG_7750_63800_66730.mp4",
"corte": "IMG_7750_63800_66730.mov",
"fuente": "IMG_7750",
"frames": 176
},
{
"file": "IMG_7750_67230_68960.mp4",
"corte": "IMG_7750_67230_68960.mov",
"fuente": "IMG_7750",
"frames": 104
},
{
"file": "IMG_7750_80970_85570.mp4",
"corte": "IMG_7750_80970_85570.mov",
"fuente": "IMG_7750",
"frames": 276
},
{
"file": "IMG_7751_19580_24849.mp4",
"corte": "IMG_7751_19580_24849.mov",
"fuente": "IMG_7751",
"frames": 317
},
{
"file": "IMG_7751_25190_30519.mp4",
"corte": "IMG_7751_25190_30519.mov",
"fuente": "IMG_7751",
"frames": 320
},
{
"file": "IMG_7751_30499_33779.mp4",
"corte": "IMG_7751_30499_33779.mov",
"fuente": "IMG_7751",
"frames": 197
},
{
"file": "IMG_7751_6879_7289.mp4",
"corte": "IMG_7751_6879_7289.mov",
"fuente": "IMG_7751",
"frames": 25
},
{
"file": "IMG_7751_7629_17299.mp4",
"corte": "IMG_7751_7629_17299.mov",
"fuente": "IMG_7751",
"frames": 581
},
{
"file": "IMG_7753_140230_146370.mp4",
"corte": "IMG_7753_140230_146370.mov",
"fuente": "IMG_7753",
"frames": 369
},
{
"file": "IMG_7753_147190_148910.mp4",
"corte": "IMG_7753_147190_148910.mov",
"fuente": "IMG_7753",
"frames": 104
},
{
"file": "IMG_7753_150370_153010.mp4",
"corte": "IMG_7753_150370_153010.mov",
"fuente": "IMG_7753",
"frames": 159
},
{
"file": "IMG_7753_154250_155030.mp4",
"corte": "IMG_7753_154250_155030.mov",
"fuente": "IMG_7753",
"frames": 47
},
{
"file": "IMG_7753_155550_155830.mp4",
"corte": "IMG_7753_155550_155830.mov",
"fuente": "IMG_7753",
"frames": 17
},
{
"file": "IMG_7753_157110_159690.mp4",
"corte": "IMG_7753_157110_159690.mov",
"fuente": "IMG_7753",
"frames": 155
},
{
"file": "IMG_7753_160070_160530.mp4",
"corte": "IMG_7753_160070_160530.mov",
"fuente": "IMG_7753",
"frames": 28
},
{
"file": "IMG_7753_161170_162530.mp4",
"corte": "IMG_7753_161170_162530.mov",
"fuente": "IMG_7753",
"frames": 82
},
{
"file": "IMG_7753_162960_163430.mp4",
"corte": "IMG_7753_162960_163430.mov",
"fuente": "IMG_7753",
"frames": 29
},
{
"file": "IMG_7753_211890_214390.mp4",
"corte": "IMG_7753_211890_214390.mov",
"fuente": "IMG_7753",
"frames": 150
},
{
"file": "IMG_7753_215270_216840.mp4",
"corte": "IMG_7753_215270_216840.mov",
"fuente": "IMG_7753",
"frames": 95
},
{
"file": "IMG_7753_220520_222470.mp4",
"corte": "IMG_7753_220520_222470.mov",
"fuente": "IMG_7753",
"frames": 117
},
{
"file": "IMG_7753_223930_224850.mp4",
"corte": "IMG_7753_223930_224850.mov",
"fuente": "IMG_7753",
"frames": 56
},
{
"file": "IMG_7753_225380_225790.mp4",
"corte": "IMG_7753_225380_225790.mov",
"fuente": "IMG_7753",
"frames": 25
},
{
"file": "IMG_7753_228170_230020.mp4",
"corte": "IMG_7753_228170_230020.mov",
"fuente": "IMG_7753",
"frames": 111
},
{
"file": "IMG_7753_232740_236280.mp4",
"corte": "IMG_7753_232740_236280.mov",
"fuente": "IMG_7753",
"frames": 213
},
{
"file": "IMG_7753_280650_287880.mp4",
"corte": "IMG_7753_280650_287880.mov",
"fuente": "IMG_7753",
"frames": 434
},
{
"file": "IMG_7753_50400_52330.mp4",
"corte": "IMG_7753_50400_52330.mov",
"fuente": "IMG_7753",
"frames": 116
},
{
"file": "IMG_7753_53050_53850.mp4",
"corte": "IMG_7753_53050_53850.mov",
"fuente": "IMG_7753",
"frames": 48
},
{
"file": "IMG_7753_54210_57780.mp4",
"corte": "IMG_7753_54210_57780.mov",
"fuente": "IMG_7753",
"frames": 215
},
{
"file": "IMG_7754_54419_55090.mp4",
"corte": "IMG_7754_54419_55090.mov",
"fuente": "IMG_7754",
"frames": 41
},
{
"file": "IMG_7754_55469_63519.mp4",
"corte": "IMG_7754_55469_63519.mov",
"fuente": "IMG_7754",
"frames": 483
},
{
"file": "IMG_7754_63879_69679.mp4",
"corte": "IMG_7754_63879_69679.mov",
"fuente": "IMG_7754",
"frames": 348
},
{
"file": "IMG_7754_74499_78769.mp4",
"corte": "IMG_7754_74499_78769.mov",
"fuente": "IMG_7754",
"frames": 257
},
{
"file": "IMG_7754_79549_85439.mp4",
"corte": "IMG_7754_79549_85439.mov",
"fuente": "IMG_7754",
"frames": 354
},
{
"file": "broll_pool.mp4",
"corte": "broll_pool.mov",
"fuente": "broll_pool",
"frames": 720
}
]